setup.py
ane_probability_dist/Binomialdistribution.py
ane_probability_dist/Gaussiandistribution.py
ane_probability_dist/Generaldistribution.py
ane_probability_dist/__init__.py
ane_probability_dist.egg-info/PKG-INFO
ane_probability_dist.egg-info/SOURCES.txt
ane_probability_dist.egg-info/dependency_links.txt
ane_probability_dist.egg-info/not-zip-safe
ane_probability_dist.egg-info/top_level.txt